{
  "request": {
    "targetHost": "queue.fal.run",
    "method": "GET",
    "pathname": "/fal-ai/elevenlabs/requests/019e1a07-0fbd-7aa2-8629-8ca23776011a",
    "bodyHash": "e3b0c44298fc1c14"
  },
  "responses": [
    {
      "status": 200,
      "headers": {
        "access-control-allow-credentials": "true",
        "connection": "keep-alive",
        "content-length": "181",
        "content-type": "application/json",
        "date": "Tue, 12 May 2026 02:32:23 GMT",
        "strict-transport-security": "max-age=31536000; includeSubDomains",
        "vary": "origin, access-control-request-method, access-control-request-headers",
        "x-fal-billable-units": "1",
        "x-fal-request-id": "019e1a07-0fbd-7aa2-8629-8ca23776011a",
        "x-fal-served-from": "25d598e5-9124-4b0c-b889-b482974b69fa",
        "x-robots-tag": "noindex"
      },
      "body": {
        "audio": {
          "url": "https://v3b.fal.media/files/b/0a99db52/4AP7rKyneFm5VJQqg3yP__music_generated.mp3",
          "content_type": "audio/mpeg",
          "file_name": "music_generated.mp3",
          "file_size": 384149
        }
      }
    }
  ]
}
